<?xml version="1.0" encoding="ISO-8859-1"?>
<attributes>
<attribute>
<srcPos sline="0" eline="0" spos="0" epos="0"/>
<jmpPos sline="98" eline="98" spos="0" epos="0"/>
<text info="[@p0, @p1, code]" aType="ParamNamesTag"/>
</attribute>
<attribute>
<srcPos sline="0" eline="0" spos="0" epos="0"/>
<jmpPos sline="116" eline="116" spos="0" epos="0"/>
<text info="[]" aType="ParamNamesTag"/>
</attribute>
<attribute>
<srcPos sline="0" eline="0" spos="0" epos="0"/>
<jmpPos sline="129" eline="129" spos="0" epos="0"/>
<text info="[code]" aType="ParamNamesTag"/>
</attribute>
<attribute>
<srcPos sline="0" eline="0" spos="0" epos="0"/>
<jmpPos sline="148" eline="148" spos="0" epos="0"/>
<text info="[]" aType="ParamNamesTag"/>
</attribute>
<attribute>
<srcPos sline="0" eline="0" spos="0" epos="0"/>
<jmpPos sline="159" eline="159" spos="0" epos="0"/>
<text info="[s]" aType="ParamNamesTag"/>
</attribute>
<attribute>
<srcPos sline="0" eline="0" spos="0" epos="0"/>
<jmpPos sline="186" eline="186" spos="0" epos="0"/>
<text info="[name]" aType="ParamNamesTag"/>
</attribute>
</attributes>
