<?xml version="1.0" encoding="ISO-8859-1"?>
<attributes>
<attribute>
<srcPos sline="0" eline="0" spos="0" epos="0"/>
<jmpPos sline="11" eline="11" spos="0" epos="0"/>
<text info="[]" aType="ParamNamesTag"/>
</attribute>
<attribute>
<srcPos sline="0" eline="0" spos="0" epos="0"/>
<jmpPos sline="31" eline="31" spos="0" epos="0"/>
<text info="[params]" aType="ParamNamesTag"/>
</attribute>
<attribute>
<srcPos sline="0" eline="0" spos="0" epos="0"/>
<jmpPos sline="592" eline="592" spos="0" epos="0"/>
<text info="[d]" aType="ParamNamesTag"/>
</attribute>
</attributes>
